quantum_cli_sdk/__init__.py
quantum_cli_sdk/app_runner.py
quantum_cli_sdk/benchmark_runner.py
quantum_cli_sdk/cache.py
quantum_cli_sdk/circuit_comparison.py
quantum_cli_sdk/cli.py
quantum_cli_sdk/config.py
quantum_cli_sdk/config_manager.py
quantum_cli_sdk/dependency_analyzer.py
quantum_cli_sdk/hardware_selector.py
quantum_cli_sdk/interactive.py
quantum_cli_sdk/job_management.py
quantum_cli_sdk/logging_config.py
quantum_cli_sdk/marketplace.py
quantum_cli_sdk/microservice_generator.py
quantum_cli_sdk/models.py
quantum_cli_sdk/output_formatter.py
quantum_cli_sdk/plugin_system.py
quantum_cli_sdk/progress.py
quantum_cli_sdk/quantum_circuit.py
quantum_cli_sdk/resource_management.py
quantum_cli_sdk/sharing.py
quantum_cli_sdk/simulator.py
quantum_cli_sdk/test_framework.py
quantum_cli_sdk/transpiler.py
quantum_cli_sdk/trial_manager.py
quantum_cli_sdk/utils.py
quantum_cli_sdk/versioning.py
quantum_cli_sdk/visualizer.py
quantum_cli_sdk/commands/__init__.py
quantum_cli_sdk/commands/benchmark.py
quantum_cli_sdk/commands/calculate_cost.py
quantum_cli_sdk/commands/estimate_resources.py
quantum_cli_sdk/commands/finetune.py
quantum_cli_sdk/commands/generate_ir.py
quantum_cli_sdk/commands/generate_microservice_tests.py
quantum_cli_sdk/commands/generate_tests.py
quantum_cli_sdk/commands/hw_run.py
quantum_cli_sdk/commands/init.py
quantum_cli_sdk/commands/microservice.py
quantum_cli_sdk/commands/package.py
quantum_cli_sdk/commands/provision.py
quantum_cli_sdk/commands/publish.py
quantum_cli_sdk/commands/run.py
quantum_cli_sdk/commands/run_app.py
quantum_cli_sdk/commands/security_scan.py
quantum_cli_sdk/commands/simulate.py
quantum_cli_sdk/commands/template.py
quantum_cli_sdk/commands/test.py
quantum_cli_sdk/commands/trial.py
quantum_cli_sdk/commands/validate.py
quantum_cli_sdk/commands/visualize.py
quantum_cli_sdk/commands/ir/mitigate.py
quantum_cli_sdk/commands/ir/optimize.py
quantum_cli_sdk/commands/simulation_backends/__init__.py
quantum_cli_sdk-0.3.7.dist-info/METADATA
quantum_cli_sdk-0.3.7.dist-info/WHEEL
quantum_cli_sdk-0.3.7.dist-info/entry_points.txt
quantum_cli_sdk-0.3.7.dist-info/top_level.txt
quantum_cli_sdk-0.3.7.dist-info/RECORD
