Metadata-Version: 2.4
Name: quantum-cli-sdk
Version: 0.3.7
Summary: A CLI and SDK for quantum development
Author-email: Abhishek Tamrakar & Mohit Saxena <trainings.abhishek@gmail.com>, Mohit Saxena <m22aie240@iitj.ac.in>
Project-URL: Homepage, https://github.com/extremecoder/quantum-cli-sdk
Project-URL: Documentation, https://github.com/extremecoder/quantum-cli-sdk/wiki
Project-URL: Source, https://github.com/extremecoder/quantum-cli-sdk
Project-URL: Tracker, https://github.com/extremecoder/quantum-cli-sdk/issues
Keywords: quantum,cli,sdk,development
Classifier: Development Status :: 3 - Alpha
Classifier: Intended Audience :: Developers
Classifier: Programming Language :: Python :: 3
Classifier: Programming Language :: Python :: 3.10
Classifier: Operating System :: OS Independent
Requires-Python: >=3.10
Requires-Dist: networkx==3.4.2
Requires-Dist: numpy==1.26.4
Requires-Dist: matplotlib==3.10.1
Requires-Dist: scipy==1.15.2
Requires-Dist: pyyaml==6.0.2
Requires-Dist: cryptography==44.0.2
Requires-Dist: click==8.1.8
Requires-Dist: qiskit==1.4.1
Requires-Dist: qiskit-aer==0.16.4
Requires-Dist: qiskit-ibm-runtime==0.36.1
Requires-Dist: qiskit-ibm-provider==0.11.0
Requires-Dist: qiskit-qasm3-import==0.5.1
Requires-Dist: qiskit-braket-provider==0.4.3
Requires-Dist: amazon-braket-sdk==1.90.1
Requires-Dist: amazon-braket-schemas==1.23.1
Requires-Dist: amazon-braket-default-simulator==1.26.4
Requires-Dist: boto3==1.37.23
Requires-Dist: cirq==1.4.1
Requires-Dist: cirq-core==1.4.1
Requires-Dist: cirq-google==1.4.1
Requires-Dist: cirq-aqt==1.4.1
Requires-Dist: cirq-ionq==1.4.1
Requires-Dist: cirq-pasqal==1.4.1
Requires-Dist: cirq-rigetti==1.4.1
Requires-Dist: cirq-web==1.4.1
Requires-Dist: protobuf==3.20.3
Requires-Dist: ply==3.11
Requires-Dist: openqasm3==1.0.1
Requires-Dist: pyyaml==6.0.2
Requires-Dist: importlib_metadata==8.6.1
Requires-Dist: rich==13.9.4
Requires-Dist: prompt_toolkit==3.0.50
Requires-Dist: plotly==6.0.1
Requires-Dist: ipython==8.34.0
Requires-Dist: jupyter==1.1.1
Requires-Dist: tqdm==4.67.1
Requires-Dist: requests==2.32.3
Requires-Dist: python-dotenv==1.1.0
Requires-Dist: seaborn==0.13.2
Requires-Dist: pandas==2.2.3
Requires-Dist: together==1.5.4
Requires-Dist: google-genai==1.10.0
Requires-Dist: fastapi==0.115.12
Requires-Dist: uvicorn==0.34.0
Requires-Dist: pydantic==2.9.2
Provides-Extra: dev
Requires-Dist: pytest>=7.0.0; extra == "dev"
Requires-Dist: flake8; extra == "dev"
Requires-Dist: black>=23.0.0; extra == "dev"
Requires-Dist: mypy; extra == "dev"
Requires-Dist: pylint>=2.17.0; extra == "dev"
